subuser-0.6.2.dist-info/RECORD
subuser-0.6.2.dist-info/WHEEL
subuser-0.6.2.dist-info/METADATA
subuser-0.6.2.dist-info/DESCRIPTION.rst
subuser-0.6.2.dist-info/top_level.txt
subuser-0.6.2.dist-info/metadata.json
subuser-0.6.2.data/scripts/execute-json-from-fifo
subuser-0.6.2.data/scripts/subuser
subuserlib/test.py
subuserlib/removeOldImages.py
subuserlib/permissions.py
subuserlib/commandLineArguments.py
subuserlib/verify.py
subuserlib/commands.py
subuserlib/subprocessExtras.py
subuserlib/resolve.py
subuserlib/terminalColors.py
subuserlib/repository.py
subuserlib/lock.py
subuserlib/print.py
subuserlib/version.py
subuserlib/registry.py
subuserlib/__init__.py
subuserlib/update.py
subuserlib/profile.py
subuserlib/subuser.py
subuserlib/loadMultiFallbackJsonConfigFile.py
subuserlib/executablePath.py
subuserlib/paths.py
subuserlib/docker.py
subuserlib/classes/service.py
subuserlib/classes/permissions.py
subuserlib/classes/exceptions.py
subuserlib/classes/config.py
subuserlib/classes/endUser.py
subuserlib/classes/imageSource.py
subuserlib/classes/userOwnedObject.py
subuserlib/classes/repository.py
subuserlib/classes/installedImage.py
subuserlib/classes/repositories.py
subuserlib/classes/fileStructure.py
subuserlib/classes/fileBackedObject.py
subuserlib/classes/subusers.py
subuserlib/classes/installationTask.py
subuserlib/classes/uhttpConnection.py
subuserlib/classes/registry.py
subuserlib/classes/__init__.py
subuserlib/classes/gitRepository.py
subuserlib/classes/subuser.py
subuserlib/classes/user.py
subuserlib/classes/installedImages.py
subuserlib/classes/describable.py
subuserlib/classes/permissionsAccepters/permissionsAccepter.py
subuserlib/classes/permissionsAccepters/acceptPermissionsAtCLI.py
subuserlib/classes/permissionsAccepters/__init__.py
subuserlib/classes/docker/mockDockerDaemon.py
subuserlib/classes/docker/container.py
subuserlib/classes/docker/__init__.py
subuserlib/classes/docker/dockerDaemon.py
subuserlib/classes/subuserSubmodules/__init__.py
subuserlib/classes/subuserSubmodules/run/runReadyImage.py
subuserlib/classes/subuserSubmodules/run/x11Bridge.py
subuserlib/classes/subuserSubmodules/run/runtimeCache.py
