Metadata-Version: 2.0
Name: subuser
Version: 0.6.2
Summary: subuser - a program which helps you run other programs in containers, securely and portably.
Home-page: http://subuser.org
Author: Timothy Hobbs
Author-email: timothy@hobbs.cz
License: LGPL-3.0
Keywords: subuser Docker containers security portability
Platform: UNKNOWN
Classifier: Development Status :: 3 - Alpha
Classifier: License :: OSI Approved :: GNU Lesser General Public License v3 (LGPLv3)
Classifier: Programming Language :: Python :: 3.0
